<?xml version="1.0" encoding="UTF-8" standalone="yes"?><imgdir name="01232033.img"><imgdir name="info"><canvas name="icon" width="41" height="41"><vector name="origin" x="0" y="36"/></canvas><canvas name="iconRaw" width="41" height="41"><vector name="origin" x="0" y="36"/></canvas><string name="islot" value="Wp"/><string name="vslot" value="Wp"/><int name="walk" value="1"/><int name="stand" value="1"/><short name="attack" value="1"/><string name="afterImage" value="swordOL"/><string name="sfx" value="swordS"/><int name="tuc" value="7"/><int name="reqJob" value="1"/><int name="reqLevel" value="95"/><int name="reqSTR" value="270"/><int name="reqDEX" value="0"/><int name="reqINT" value="0"/><int name="reqLUK" value="0"/><int name="incPAD" value="110"/><int name="price" value="43000"/><int name="attackSpeed" value="6"/><int name="cash" value="0"/><int name="incPVPDamage" value="5"/><int name="expireOnLogout" value="1"/><int name="notSale" value="1"/><int name="only" value="1"/><int name="tradeBlock" value="1"/></imgdir><imgdir name="walk1"><imgdir name="0"><canvas name="weapon" width="69" height="69"><vector name="origin" x="43" y="43"/><imgdir name="map"><vector name="hand" x="0" y="0"/></imgdir><string name="z" value="weaponBelowBody"/></canvas></imgdir><imgdir name="1"><canvas name="weapon" width="69" height="69"><vector name="origin" x="34" y="44"/><imgdir name="map"><vector name="hand" x="0" y="0"/></imgdir><string name="z" value="weaponBelowBody"/></canvas></imgdir><imgdir name="2"><canvas name="weapon" width="69" height="69"><vector name="origin" x="43" y="43"/><imgdir name="map"><vector name="hand" x="0" y="0"/></imgdir><string name="z" value="weaponBelowBody"/></canvas></imgdir><imgdir name="3"><canvas name="weapon" width="69" height="69"><vector name="origin" x="46" y="41"/><imgdir name="map"><vector name="hand" x="0" y="0"/></imgdir><string name="z" value="weaponBelowBody"/></canvas></imgdir></imgdir><imgdir name="stand1"><imgdir name="0"><canvas name="weapon" width="69" height="69"><vector name="origin" x="40" y="44"/><imgdir name="map"><vector name="hand" x="0" y="0"/></imgdir><string name="z" value="weaponBelowBody"/></canvas></imgdir><imgdir name="1"><canvas name="weapon" width="69" height="69"><vector name="origin" x="42" y="44"/><imgdir name="map"><vector name="hand" x="0" y="0"/></imgdir><string name="z" value="weaponBelowBody"/></canvas></imgdir><imgdir name="2"><canvas name="weapon" width="69" height="69"><vector name="origin" x="44" y="44"/><imgdir name="map"><vector name="hand" x="0" y="0"/></imgdir><string name="z" value="weaponBelowBody"/></canvas></imgdir></imgdir><imgdir name="alert"><imgdir name="0"><canvas name="weapon" width="88" height="44"><vector name="origin" x="71" y="33"/><imgdir name="map"><vector name="hand" x="0" y="0"/></imgdir><string name="z" value="weaponOverHand"/></canvas></imgdir><imgdir name="1"><canvas name="weapon" width="88" height="44"><vector name="origin" x="70" y="32"/><imgdir name="map"><vector name="hand" x="0" y="0"/></imgdir><string name="z" value="weaponOverHand"/></canvas></imgdir><imgdir name="2"><canvas name="weapon" width="88" height="44"><vector name="origin" x="71" y="31"/><imgdir name="map"><vector name="hand" x="0" y="0"/></imgdir><string name="z" value="weaponOverHand"/></canvas></imgdir></imgdir><imgdir name="swingO1"><imgdir name="0"><canvas name="weapon" width="89" height="29"><vector name="origin" x="19" y="17"/><imgdir name="map"><vector name="hand" x="0" y="0"/></imgdir><string name="z" value="weaponBelowBody"/></canvas></imgdir><imgdir name="1"><canvas name="weapon" width="87" height="43"><vector name="origin" x="18" y="14"/><imgdir name="map"><vector name="hand" x="0" y="0"/></imgdir><string name="z" value="weaponBelowBody"/></canvas></imgdir><imgdir name="2"><canvas name="weapon" width="68" height="67"><vector name="origin" x="13" y="54"/><imgdir name="map"><vector name="hand" x="0" y="0"/></imgdir><string name="z" value="weapon"/></canvas></imgdir></imgdir><imgdir name="swingO2"><imgdir name="0"><canvas name="weapon" width="69" height="69"><vector name="origin" x="13" y="54"/><imgdir name="map"><vector name="hand" x="0" y="0"/></imgdir><string name="z" value="weaponBelowBody"/></canvas></imgdir><imgdir name="1"><canvas name="weapon" width="43" height="87"><vector name="origin" x="12" y="77"/><imgdir name="map"><vector name="hand" x="0" y="0"/></imgdir><string name="z" value="weaponBelowBody"/></canvas></imgdir><imgdir name="2"><canvas name="weapon" width="43" height="87"><vector name="origin" x="32" y="19"/><imgdir name="map"><vector name="hand" x="0" y="0"/></imgdir><string name="z" value="weapon"/></canvas></imgdir></imgdir><imgdir name="swingO3"><imgdir name="0"><canvas name="weapon" width="43" height="87"><vector name="origin" x="13" y="68"/><imgdir name="map"><vector name="hand" x="0" y="0"/></imgdir><string name="z" value="weapon"/></canvas></imgdir><imgdir name="1"><canvas name="weapon" width="95" height="15"><vector name="origin" x="75" y="7"/><imgdir name="map"><vector name="hand" x="0" y="0"/></imgdir><string name="z" value="weaponOverBody"/></canvas></imgdir><imgdir name="2"><canvas name="weapon" width="93" height="15"><vector name="origin" x="9" y="10"/><imgdir name="map"><vector name="hand" x="0" y="0"/></imgdir><string name="z" value="weaponBelowBody"/></canvas></imgdir></imgdir><imgdir name="swingOF"><imgdir name="0"><canvas name="weapon" width="43" height="87"><vector name="origin" x="13" y="20"/><imgdir name="map"><vector name="hand" x="0" y="0"/></imgdir><string name="z" value="weapon"/></canvas></imgdir><imgdir name="1"><canvas name="weapon" width="69" height="69"><vector name="origin" x="33" y="71"/><imgdir name="map"><vector name="hand" x="0" y="0"/></imgdir><string name="z" value="backWeapon"/></canvas></imgdir><imgdir name="2"><canvas name="weapon" width="88" height="44"><vector name="origin" x="10" y="34"/><imgdir name="map"><vector name="hand" x="0" y="0"/></imgdir><string name="z" value="weaponBelowBody"/></canvas></imgdir><imgdir name="3"><canvas name="weapon" width="91" height="30"><vector name="origin" x="20" y="25"/><imgdir name="map"><vector name="hand" x="0" y="0"/></imgdir><string name="z" value="weaponBelowBody"/></canvas></imgdir></imgdir><imgdir name="stabO1"><imgdir name="0"><canvas name="weapon" width="90" height="29"><vector name="origin" x="71" y="15"/><imgdir name="map"><vector name="hand" x="0" y="0"/></imgdir><string name="z" value="weapon"/></canvas></imgdir><imgdir name="1"><canvas name="weapon" width="95" height="15"><vector name="origin" x="74" y="8"/><imgdir name="map"><vector name="hand" x="0" y="0"/></imgdir><string name="z" value="weapon"/></canvas></imgdir></imgdir><imgdir name="stabO2"><imgdir name="0"><canvas name="weapon" width="95" height="15"><vector name="origin" x="77" y="6"/><imgdir name="map"><vector name="hand" x="0" y="0"/></imgdir><string name="z" value="weaponBelowArm"/></canvas></imgdir><imgdir name="1"><canvas name="weapon" width="90" height="29"><vector name="origin" x="72" y="13"/><imgdir name="map"><vector name="hand" x="0" y="0"/></imgdir><string name="z" value="weapon"/></canvas></imgdir></imgdir><imgdir name="stabOF"><imgdir name="0"><canvas name="weapon" width="90" height="29"><vector name="origin" x="71" y="15"/><imgdir name="map"><vector name="hand" x="0" y="0"/></imgdir><string name="z" value="weapon"/></canvas></imgdir><imgdir name="1"><canvas name="weapon" width="90" height="29"><vector name="origin" x="37" y="19"/><imgdir name="map"><vector name="hand" x="0" y="0"/></imgdir><string name="z" value="weapon"/></canvas></imgdir><imgdir name="2"><canvas name="weapon" width="95" height="15"><vector name="origin" x="81" y="20"/><imgdir name="map"><vector name="hand" x="0" y="0"/></imgdir><string name="z" value="weapon"/></canvas></imgdir></imgdir><imgdir name="proneStab"><imgdir name="0"><canvas name="weapon" width="90" height="29"><vector name="origin" x="72" y="13"/><imgdir name="map"><vector name="hand" x="0" y="0"/></imgdir><string name="z" value="weaponBelowArm"/></canvas></imgdir><imgdir name="1"><canvas name="weapon" width="90" height="29"><vector name="origin" x="72" y="14"/><imgdir name="map"><vector name="hand" x="0" y="0"/></imgdir><string name="z" value="weaponBelowArm"/></canvas></imgdir></imgdir><imgdir name="prone"><imgdir name="0"><uol name="weapon" value="../../proneStab/0/weapon"/></imgdir></imgdir><imgdir name="heal"><imgdir name="0"><uol name="weapon" value="../../alert/1/weapon"/></imgdir><imgdir name="1"><uol name="weapon" value="../../swingO2/1/weapon"/></imgdir><imgdir name="2"><uol name="weapon" value="../../swingO2/0/weapon"/></imgdir></imgdir><imgdir name="fly"><imgdir name="0"><canvas name="weapon" width="69" height="69"><vector name="origin" x="35" y="31"/><imgdir name="map"><vector name="hand" x="0" y="0"/></imgdir><string name="z" value="weaponBelowBody"/></canvas></imgdir><imgdir name="1"><canvas name="weapon" width="69" height="69"><vector name="origin" x="34" y="32"/><imgdir name="map"><vector name="hand" x="0" y="0"/></imgdir><string name="z" value="weaponBelowBody"/></canvas></imgdir></imgdir><imgdir name="jump"><imgdir name="0"><canvas name="weapon" width="69" height="69"><vector name="origin" x="35" y="31"/><imgdir name="map"><vector name="hand" x="0" y="0"/></imgdir><string name="z" value="weaponBelowBody"/></canvas></imgdir></imgdir><imgdir name="ladder"><imgdir name="0"><canvas name="weapon" width="69" height="69"><vector name="origin" x="34" y="34"/><imgdir name="map"><vector name="muzzle" x="24" y="-26"/><vector name="navel" x="0" y="0"/></imgdir><string name="z" value="weaponBelowBody"/></canvas></imgdir><imgdir name="1"><canvas name="weapon" width="69" height="69"><vector name="origin" x="34" y="34"/><imgdir name="map"><vector name="muzzle" x="25" y="-26"/><vector name="navel" x="0" y="0"/></imgdir><string name="z" value="weaponBelowBody"/></canvas></imgdir></imgdir><imgdir name="rope"><imgdir name="0"><canvas name="weapon" width="69" height="69"><vector name="origin" x="34" y="34"/><imgdir name="map"><vector name="muzzle" x="26" y="-28"/><vector name="navel" x="0" y="0"/></imgdir><string name="z" value="weaponBelowBody"/></canvas></imgdir><imgdir name="1"><canvas name="weapon" width="69" height="69"><vector name="origin" x="34" y="34"/><imgdir name="map"><vector name="muzzle" x="27" y="-29"/><vector name="navel" x="0" y="0"/></imgdir><string name="z" value="weaponBelowBody"/></canvas></imgdir></imgdir></imgdir>