<?xml version="1.0" encoding="UTF-8" standalone="yes"?><imgdir name="01462091.img"><imgdir name="info"><canvas name="icon" width="36" height="36"><vector name="origin" x="2" y="34"/></canvas><canvas name="iconRaw" width="36" height="36"><vector name="origin" x="2" y="34"/></canvas><string name="islot" value="WpSi"/><string name="vslot" value="WpSi"/><int name="walk" value="2"/><int name="stand" value="2"/><short name="attack" value="4"/><string name="afterImage" value="crossBow"/><string name="sfx" value="cBow"/><int name="reqJob" value="4"/><int name="reqLevel" value="127"/><int name="reqSTR" value="0"/><int name="reqDEX" value="0"/><int name="reqINT" value="0"/><int name="reqLUK" value="0"/><int name="incPAD" value="118"/><int name="tuc" value="7"/><int name="price" value="550000"/><int name="attackSpeed" value="6"/><int name="cash" value="0"/><int name="knockback" value="70"/><int name="incDEX" value="8"/><int name="incSTR" value="4"/><int name="incSpeed" value="14"/></imgdir><imgdir name="walk2"><imgdir name="0"><canvas name="weapon" width="55" height="55"><vector name="origin" x="20" y="5"/><imgdir name="map"><vector name="navel" x="12" y="18"/></imgdir><string name="z" value="weaponOverArm"/></canvas></imgdir><imgdir name="1"><canvas name="weapon" width="54" height="54"><vector name="origin" x="27" y="3"/><imgdir name="map"><vector name="navel" x="5" y="18"/></imgdir><string name="z" value="weaponOverArm"/></canvas></imgdir><imgdir name="2"><uol name="weapon" value="../0/weapon"/></imgdir><imgdir name="3"><canvas name="weapon" width="54" height="54"><vector name="origin" x="25" y="3"/><imgdir name="map"><vector name="navel" x="5" y="20"/></imgdir><string name="z" value="weaponOverArm"/></canvas></imgdir></imgdir><imgdir name="stand2"><imgdir name="0"><canvas name="weapon" width="55" height="55"><vector name="origin" x="26" y="7"/><imgdir name="map"><vector name="navel" x="5" y="17"/></imgdir><string name="z" value="weaponOverArm"/></canvas></imgdir><imgdir name="1"><canvas name="weapon" width="54" height="54"><vector name="origin" x="25" y="7"/><imgdir name="map"><vector name="navel" x="5" y="18"/></imgdir><string name="z" value="weaponOverArm"/></canvas></imgdir><imgdir name="2"><canvas name="weapon" width="54" height="54"><vector name="origin" x="25" y="7"/><imgdir name="map"><vector name="navel" x="5" y="17"/></imgdir><string name="z" value="weaponOverArm"/></canvas></imgdir></imgdir><imgdir name="alert"><imgdir name="0"><canvas name="weapon" width="59" height="26"><vector name="origin" x="12" y="7"/><imgdir name="map"><vector name="navel" x="23" y="5"/></imgdir><string name="z" value="weaponBelowArm"/></canvas></imgdir><imgdir name="1"><canvas name="weapon" width="59" height="26"><vector name="origin" x="12" y="7"/><imgdir name="map"><vector name="navel" x="23" y="3"/></imgdir><string name="z" value="weaponBelowArm"/></canvas></imgdir><imgdir name="2"><canvas name="weapon" width="58" height="23"><vector name="origin" x="12" y="6"/><imgdir name="map"><vector name="navel" x="23" y="1"/></imgdir><string name="z" value="weaponBelowArm"/></canvas></imgdir></imgdir><imgdir name="swingT1"><imgdir name="0"><canvas name="weapon" width="56" height="26"><vector name="origin" x="18" y="2"/><imgdir name="map"><vector name="navel" x="-18" y="36"/></imgdir><string name="z" value="weapon"/></canvas></imgdir><imgdir name="1"><canvas name="weapon" width="57" height="57"><vector name="origin" x="17" y="4"/><imgdir name="map"><vector name="navel" x="11" y="56"/></imgdir><string name="z" value="weaponBelowArm"/></canvas></imgdir><imgdir name="2"><canvas name="weapon" width="105" height="122"><vector name="origin" x="58" y="106"/><imgdir name="map"><vector name="navel" x="41" y="-11"/></imgdir><string name="z" value="weapon"/></canvas></imgdir></imgdir><imgdir name="stabT1"><imgdir name="0"><canvas name="weapon" width="56" height="26"><vector name="origin" x="18" y="7"/><imgdir name="map"><vector name="navel" x="9" y="5"/></imgdir><string name="z" value="weaponOverBody"/></canvas></imgdir><imgdir name="1"><canvas name="weapon" width="56" height="26"><vector name="origin" x="20" y="7"/><imgdir name="map"><vector name="navel" x="11" y="4"/></imgdir><string name="z" value="weaponOverBody"/></canvas></imgdir><imgdir name="2"><canvas name="weapon" width="85" height="27"><vector name="origin" x="21" y="8"/><imgdir name="map"><vector name="navel" x="32" y="9"/></imgdir><string name="z" value="weaponOverBody"/></canvas></imgdir></imgdir><imgdir name="proneStab"><imgdir name="0"><canvas name="weapon" width="59" height="26"><vector name="origin" x="5" y="6"/><imgdir name="map"><vector name="navel" x="44" y="9"/></imgdir><string name="z" value="weaponBelowArm"/></canvas></imgdir><imgdir name="1"><canvas name="weapon" width="89" height="27"><vector name="origin" x="3" y="6"/><imgdir name="map"><vector name="navel" x="60" y="9"/></imgdir><string name="z" value="weaponBelowArm"/></canvas></imgdir></imgdir><imgdir name="fly"><imgdir name="0"><canvas name="weapon" width="55" height="55"><vector name="origin" x="33" y="6"/><imgdir name="map"><vector name="navel" x="3" y="24"/></imgdir><string name="z" value="weaponOverArm"/></canvas></imgdir><imgdir name="1"><uol name="weapon" value="../0/weapon"/></imgdir></imgdir><imgdir name="jump"><imgdir name="0"><canvas name="weapon" width="55" height="55"><vector name="origin" x="37" y="7"/><imgdir name="map"><vector name="navel" x="-2" y="22"/></imgdir><string name="z" value="weaponOverArm"/></canvas></imgdir></imgdir><imgdir name="shoot2"><imgdir name="0"><canvas name="weapon" width="59" height="26"><vector name="origin" x="17" y="8"/><imgdir name="map"><vector name="navel" x="20" y="11"/></imgdir><string name="z" value="weapon"/></canvas></imgdir><imgdir name="1"><canvas name="weapon" width="191" height="128"><vector name="origin" x="86" y="76"/><imgdir name="map"><vector name="navel" x="20" y="11"/></imgdir><string name="z" value="weapon"/></canvas></imgdir><imgdir name="2"><canvas name="weapon" width="221" height="141"><vector name="origin" x="102" y="82"/><imgdir name="map"><vector name="navel" x="20" y="11"/></imgdir><string name="z" value="weapon"/></canvas></imgdir><imgdir name="3"><canvas name="weapon" width="155" height="143"><vector name="origin" x="115" y="85"/><imgdir name="map"><vector name="navel" x="18" y="11"/></imgdir><string name="z" value="weapon"/></canvas></imgdir><imgdir name="4"><canvas name="weapon" width="59" height="26"><vector name="origin" x="18" y="8"/><imgdir name="map"><vector name="navel" x="18" y="11"/></imgdir><string name="z" value="weapon"/></canvas></imgdir></imgdir><imgdir name="prone"><imgdir name="0"><uol name="weapon" value="../../proneStab/0/weapon"/></imgdir></imgdir></imgdir>