<?xml version="1.0" encoding="UTF-8" standalone="yes"?><imgdir name="0085.img"><imgdir name="info"><int name="speed" value="100"/><int name="jump" value="100"/><float name="fs" value="10.0"/><float name="swim" value="100.0"/><int name="noCancelDamage" value="1"/></imgdir><imgdir name="walk"><canvas name="0" width="231" height="194"><vector name="origin" x="110" y="192"/><vector name="lt" x="-110" y="-179"/><vector name="rb" x="121" y="1"/><vector name="head" x="-13" y="-149"/><int name="delay" value="120"/></canvas><canvas name="1" width="233" height="192"><vector name="origin" x="111" y="191"/><vector name="lt" x="-110" y="-179"/><vector name="rb" x="121" y="1"/><vector name="head" x="-13" y="-149"/><int name="delay" value="120"/></canvas><canvas name="2" width="237" height="190"><vector name="origin" x="112" y="188"/><vector name="lt" x="-110" y="-179"/><vector name="rb" x="121" y="1"/><vector name="head" x="-13" y="-149"/><int name="delay" value="120"/></canvas><canvas name="3" width="233" height="184"><vector name="origin" x="111" y="183"/><vector name="lt" x="-110" y="-179"/><vector name="rb" x="121" y="1"/><vector name="head" x="-13" y="-149"/><int name="delay" value="120"/></canvas><canvas name="4" width="231" height="188"><vector name="origin" x="110" y="187"/><vector name="lt" x="-110" y="-179"/><vector name="rb" x="121" y="1"/><vector name="head" x="-13" y="-149"/><int name="delay" value="120"/></canvas></imgdir><imgdir name="stand"><canvas name="0" width="231" height="194"><vector name="origin" x="110" y="192"/><vector name="lt" x="-110" y="-180"/><vector name="rb" x="120" y="1"/><vector name="head" x="-13" y="-146"/><int name="delay" value="150"/></canvas><canvas name="1" width="231" height="193"><vector name="origin" x="110" y="191"/><vector name="lt" x="-110" y="-180"/><vector name="rb" x="120" y="1"/><vector name="head" x="-13" y="-146"/><int name="delay" value="150"/></canvas><canvas name="2" width="231" height="190"><vector name="origin" x="110" y="188"/><vector name="lt" x="-110" y="-180"/><vector name="rb" x="120" y="1"/><vector name="head" x="-13" y="-146"/><int name="delay" value="150"/></canvas><canvas name="3" width="231" height="185"><vector name="origin" x="110" y="183"/><vector name="lt" x="-110" y="-180"/><vector name="rb" x="120" y="1"/><vector name="head" x="-13" y="-146"/><int name="delay" value="150"/></canvas><canvas name="4" width="231" height="189"><vector name="origin" x="110" y="187"/><vector name="lt" x="-110" y="-180"/><vector name="rb" x="120" y="1"/><vector name="head" x="-13" y="-146"/><int name="delay" value="150"/></canvas><canvas name="5" width="231" height="194"><vector name="origin" x="110" y="192"/><vector name="lt" x="-110" y="-180"/><vector name="rb" x="120" y="1"/><vector name="head" x="-13" y="-146"/><int name="delay" value="150"/></canvas><canvas name="6" width="231" height="193"><vector name="origin" x="110" y="191"/><vector name="lt" x="-110" y="-180"/><vector name="rb" x="120" y="1"/><vector name="head" x="-13" y="-146"/><int name="delay" value="150"/></canvas><canvas name="7" width="231" height="190"><vector name="origin" x="110" y="188"/><vector name="lt" x="-110" y="-180"/><vector name="rb" x="120" y="1"/><vector name="head" x="-13" y="-146"/><int name="delay" value="150"/></canvas><canvas name="8" width="231" height="185"><vector name="origin" x="110" y="183"/><vector name="lt" x="-110" y="-180"/><vector name="rb" x="120" y="1"/><vector name="head" x="-13" y="-146"/><int name="delay" value="150"/></canvas><canvas name="9" width="231" height="184"><vector name="origin" x="110" y="182"/><vector name="lt" x="-110" y="-180"/><vector name="rb" x="120" y="1"/><vector name="head" x="-13" y="-146"/><int name="delay" value="150"/></canvas></imgdir><imgdir name="prone"><canvas name="0" width="231" height="185"><vector name="origin" x="110" y="183"/><vector name="lt" x="-110" y="-180"/><vector name="rb" x="120" y="1"/><vector name="head" x="-13" y="-146"/><int name="delay" value="150"/></canvas></imgdir><imgdir name="fly"><canvas name="0" width="231" height="194"><vector name="origin" x="110" y="192"/><vector name="lt" x="-110" y="-179"/><vector name="rb" x="121" y="1"/><vector name="head" x="-13" y="-149"/><int name="delay" value="120"/></canvas><canvas name="1" width="233" height="192"><vector name="origin" x="111" y="191"/><vector name="lt" x="-110" y="-179"/><vector name="rb" x="121" y="1"/><vector name="head" x="-13" y="-149"/><int name="delay" value="120"/></canvas><canvas name="2" width="237" height="190"><vector name="origin" x="112" y="188"/><vector name="lt" x="-110" y="-179"/><vector name="rb" x="121" y="1"/><vector name="head" x="-13" y="-149"/><int name="delay" value="120"/></canvas><canvas name="3" width="233" height="184"><vector name="origin" x="111" y="183"/><vector name="lt" x="-110" y="-179"/><vector name="rb" x="121" y="1"/><vector name="head" x="-13" y="-149"/><int name="delay" value="120"/></canvas><canvas name="4" width="231" height="188"><vector name="origin" x="110" y="187"/><vector name="lt" x="-110" y="-179"/><vector name="rb" x="121" y="1"/><vector name="head" x="-13" y="-149"/><int name="delay" value="120"/></canvas></imgdir><imgdir name="jump"><canvas name="0" width="233" height="184"><vector name="origin" x="111" y="183"/><vector name="lt" x="-110" y="-179"/><vector name="rb" x="121" y="1"/><vector name="head" x="-13" y="-149"/><int name="delay" value="120"/></canvas></imgdir></imgdir>