<?xml version="1.0" encoding="UTF-8" standalone="yes"?><imgdir name="01092112.img"><imgdir name="info"><canvas name="icon" width="31" height="31"><vector name="origin" x="-1" y="31"/></canvas><canvas name="iconRaw" width="31" height="30"><vector name="origin" x="-1" y="31"/></canvas><string name="islot" value="Si"/><string name="vslot" value="Si"/><int name="reqJob" value="0"/><int name="reqLevel" value="0"/><int name="reqSTR" value="0"/><int name="reqDEX" value="0"/><int name="reqINT" value="0"/><int name="reqLUK" value="0"/><int name="cash" value="1"/></imgdir><imgdir name="walk1"><imgdir name="0"><canvas name="shield" width="33" height="52"><vector name="origin" x="36" y="37"/><imgdir name="map"><vector name="navel" x="0" y="0"/></imgdir><string name="z" value="shield"/></canvas></imgdir><imgdir name="1"><canvas name="shield" width="31" height="46"><vector name="origin" x="29" y="30"/><imgdir name="map"><vector name="navel" x="0" y="0"/></imgdir><string name="z" value="shield"/></canvas></imgdir><imgdir name="2"><canvas name="shield" width="31" height="45"><vector name="origin" x="34" y="30"/><imgdir name="map"><vector name="navel" x="0" y="0"/></imgdir><string name="z" value="shield"/></canvas></imgdir><imgdir name="3"><canvas name="shield" width="32" height="47"><vector name="origin" x="36" y="38"/><imgdir name="map"><vector name="navel" x="0" y="0"/></imgdir><string name="z" value="shield"/></canvas></imgdir></imgdir><imgdir name="stand1"><imgdir name="0"><canvas name="shield" width="32" height="44"><vector name="origin" x="21" y="24"/><imgdir name="map"><vector name="navel" x="0" y="0"/></imgdir><string name="z" value="shieldBelowBody"/></canvas></imgdir><imgdir name="1"><canvas name="shield" width="32" height="33"><vector name="origin" x="23" y="14"/><imgdir name="map"><vector name="navel" x="0" y="0"/></imgdir><string name="z" value="shieldBelowBody"/></canvas></imgdir><imgdir name="2"><canvas name="shield" width="32" height="37"><vector name="origin" x="25" y="17"/><imgdir name="map"><vector name="navel" x="0" y="0"/></imgdir><string name="z" value="shieldBelowBody"/></canvas></imgdir></imgdir><imgdir name="alert"><imgdir name="0"><canvas name="shield" width="33" height="52"><vector name="origin" x="39" y="40"/><imgdir name="map"><vector name="navel" x="0" y="0"/></imgdir><string name="z" value="shieldOverHair"/></canvas></imgdir><imgdir name="1"><canvas name="shield" width="31" height="46"><vector name="origin" x="37" y="32"/><imgdir name="map"><vector name="navel" x="0" y="0"/></imgdir><string name="z" value="shieldOverHair"/></canvas></imgdir><imgdir name="2"><canvas name="shield" width="31" height="45"><vector name="origin" x="37" y="29"/><imgdir name="map"><vector name="navel" x="0" y="0"/></imgdir><string name="z" value="shieldOverHair"/></canvas></imgdir></imgdir><imgdir name="swingO1"><imgdir name="0"><canvas name="shield" width="38" height="33"><vector name="origin" x="21" y="18"/><imgdir name="map"><vector name="navel" x="0" y="0"/></imgdir><string name="z" value="shieldBelowBody"/></canvas><canvas name="effect" width="20" height="9"><vector name="origin" x="18" y="6"/><imgdir name="map"><vector name="navel" x="0" y="0"/></imgdir><string name="z" value="characterStart"/></canvas></imgdir><imgdir name="1"><canvas name="shield" width="48" height="35"><vector name="origin" x="22" y="16"/><imgdir name="map"><vector name="navel" x="0" y="0"/></imgdir><string name="z" value="shieldBelowBody"/></canvas><canvas name="effect" width="29" height="12"><vector name="origin" x="19" y="5"/><imgdir name="map"><vector name="navel" x="0" y="0"/></imgdir><string name="z" value="characterStart"/></canvas></imgdir><imgdir name="2"><canvas name="shield" width="37" height="34"><vector name="origin" x="27" y="18"/><imgdir name="map"><vector name="navel" x="0" y="0"/></imgdir><string name="z" value="shieldBelowBody"/></canvas><canvas name="effect" width="19" height="11"><vector name="origin" x="24" y="7"/><imgdir name="map"><vector name="navel" x="0" y="0"/></imgdir><string name="z" value="characterStart"/></canvas></imgdir></imgdir><imgdir name="swingO2"><imgdir name="0"><canvas name="shield" width="37" height="34"><vector name="origin" x="30" y="11"/><imgdir name="map"><vector name="navel" x="0" y="0"/></imgdir><string name="z" value="shieldBelowBody"/></canvas><canvas name="effect" width="19" height="11"><vector name="origin" x="27" y="0"/><imgdir name="map"><vector name="navel" x="0" y="0"/></imgdir><string name="z" value="characterStart"/></canvas></imgdir><imgdir name="1"><canvas name="shield" width="32" height="37"><vector name="origin" x="24" y="21"/><imgdir name="map"><vector name="navel" x="0" y="0"/></imgdir><string name="z" value="shieldBelowBody"/></canvas><canvas name="effect" width="13" height="14"><vector name="origin" x="20" y="10"/><imgdir name="map"><vector name="navel" x="0" y="0"/></imgdir><string name="z" value="characterStart"/></canvas></imgdir><imgdir name="2"><canvas name="shield" width="32" height="37"><vector name="origin" x="32" y="24"/><imgdir name="map"><vector name="navel" x="0" y="0"/></imgdir><string name="z" value="shieldBelowBody"/></canvas><canvas name="effect" width="16" height="14"><vector name="origin" x="24" y="13"/><imgdir name="map"><vector name="navel" x="0" y="0"/></imgdir><string name="z" value="characterStart"/></canvas></imgdir></imgdir><imgdir name="swingO3"><imgdir name="0"><canvas name="shield" width="32" height="36"><vector name="origin" x="40" y="19"/><imgdir name="map"><vector name="navel" x="0" y="0"/></imgdir><string name="z" value="shieldBelowBody"/></canvas><canvas name="effect" width="16" height="14"><vector name="origin" x="33" y="9"/><imgdir name="map"><vector name="navel" x="0" y="0"/></imgdir><string name="z" value="characterStart"/></canvas></imgdir><imgdir name="1"><canvas name="shield" width="45" height="35"><vector name="origin" x="30" y="21"/><imgdir name="map"><vector name="navel" x="0" y="0"/></imgdir><string name="z" value="shieldBelowBody"/></canvas><canvas name="effect" width="23" height="13"><vector name="origin" x="27" y="11"/><imgdir name="map"><vector name="navel" x="0" y="0"/></imgdir><string name="z" value="characterStart"/></canvas></imgdir><imgdir name="2"><canvas name="shield" width="36" height="38"><vector name="origin" x="14" y="18"/><imgdir name="map"><vector name="navel" x="0" y="0"/></imgdir><string name="z" value="shieldBelowBody"/></canvas><canvas name="effect" width="17" height="14"><vector name="origin" x="11" y="6"/><imgdir name="map"><vector name="navel" x="0" y="0"/></imgdir><string name="z" value="characterStart"/></canvas></imgdir></imgdir><imgdir name="swingOF"><imgdir name="0"><canvas name="shield" width="35" height="30"><vector name="origin" x="37" y="18"/><imgdir name="map"><vector name="navel" x="0" y="0"/></imgdir><string name="z" value="shieldBelowBody"/></canvas></imgdir><imgdir name="1"><canvas name="shield" width="41" height="30"><vector name="origin" x="-7" y="19"/><imgdir name="map"><vector name="navel" x="0" y="0"/></imgdir><string name="z" value="backShield"/></canvas></imgdir><imgdir name="2"><canvas name="shield" width="40" height="36"><vector name="origin" x="12" y="22"/><imgdir name="map"><vector name="navel" x="0" y="0"/></imgdir><string name="z" value="shieldBelowBody"/></canvas></imgdir><imgdir name="3"><canvas name="shield" width="32" height="34"><vector name="origin" x="37" y="17"/><imgdir name="map"><vector name="navel" x="0" y="0"/></imgdir><string name="z" value="shieldBelowBody"/></canvas></imgdir></imgdir><imgdir name="ladder"><imgdir name="0"><canvas name="shield" width="31" height="30"><vector name="origin" x="18" y="20"/><imgdir name="map"><vector name="navel" x="0" y="0"/></imgdir><string name="z" value="backShield"/></canvas></imgdir><imgdir name="1"><canvas name="shield" width="31" height="30"><vector name="origin" x="17" y="20"/><imgdir name="map"><vector name="navel" x="0" y="0"/></imgdir><string name="z" value="backShield"/></canvas></imgdir></imgdir><imgdir name="stabO1"><imgdir name="0"><canvas name="shield" width="45" height="30"><vector name="origin" x="60" y="21"/><imgdir name="map"><vector name="navel" x="0" y="0"/></imgdir><string name="z" value="shieldBelowBody"/></canvas></imgdir><imgdir name="1"><canvas name="shield" width="48" height="33"><vector name="origin" x="31" y="19"/><imgdir name="map"><vector name="navel" x="0" y="0"/></imgdir><string name="z" value="shieldBelowBody"/></canvas></imgdir></imgdir><imgdir name="stabO2"><imgdir name="0"><canvas name="shield" width="45" height="30"><vector name="origin" x="22" y="15"/><imgdir name="map"><vector name="navel" x="0" y="0"/></imgdir><string name="z" value="shieldBelowBody"/></canvas></imgdir><imgdir name="1"><canvas name="shield" width="50" height="32"><vector name="origin" x="34" y="18"/><imgdir name="map"><vector name="navel" x="0" y="0"/></imgdir><string name="z" value="shieldBelowBody"/></canvas></imgdir></imgdir><imgdir name="proneStab"><imgdir name="0"><canvas name="shield" width="31" height="31"><vector name="origin" x="51" y="24"/><imgdir name="map"><vector name="navel" x="0" y="0"/></imgdir><string name="z" value="shieldBelowBody"/></canvas></imgdir><imgdir name="1"><uol name="shield" value="../0/shield"/></imgdir></imgdir><imgdir name="fly"><imgdir name="0"><canvas name="shield" width="32" height="29"><vector name="origin" x="24" y="17"/><imgdir name="map"><vector name="navel" x="0" y="0"/></imgdir><string name="z" value="shieldBelowBody"/></canvas></imgdir><imgdir name="1"><uol name="shield" value="../0/shield"/></imgdir></imgdir><imgdir name="jump"><imgdir name="0"><canvas name="shield" width="32" height="29"><vector name="origin" x="23" y="16"/><imgdir name="map"><vector name="navel" x="0" y="0"/></imgdir><string name="z" value="shieldBelowBody"/></canvas></imgdir></imgdir><imgdir name="stabOF"><imgdir name="0"><canvas name="shield" width="33" height="31"><vector name="origin" x="32" y="18"/><imgdir name="map"><vector name="navel" x="0" y="0"/></imgdir><string name="z" value="shield"/></canvas></imgdir><imgdir name="1"><canvas name="shield" width="32" height="38"><vector name="origin" x="47" y="22"/><imgdir name="map"><vector name="navel" x="0" y="0"/></imgdir><string name="z" value="shieldBelowBody"/></canvas></imgdir><imgdir name="2"><canvas name="shield" width="40" height="33"><vector name="origin" x="43" y="19"/><imgdir name="map"><vector name="navel" x="0" y="0"/></imgdir><string name="z" value="shieldBelowBody"/></canvas></imgdir></imgdir><imgdir name="rope"><imgdir name="0"><canvas name="shield" width="31" height="30"><vector name="origin" x="18" y="17"/><imgdir name="map"><vector name="navel" x="0" y="0"/></imgdir><string name="z" value="backShield"/></canvas></imgdir><imgdir name="1"><canvas name="shield" width="31" height="30"><vector name="origin" x="17" y="21"/><imgdir name="map"><vector name="navel" x="0" y="0"/></imgdir><string name="z" value="backShield"/></canvas></imgdir></imgdir><imgdir name="prone"><imgdir name="0"><uol name="shield" value="../../proneStab/0/shield"/></imgdir></imgdir><imgdir name="heal"><imgdir name="0"><uol name="shield" value="../../alert/1/shield"/></imgdir><imgdir name="1"><uol name="shield" value="../../swingO2/1/shield"/></imgdir><imgdir name="2"><uol name="shield" value="../../swingO2/0/shield"/></imgdir></imgdir></imgdir>