<?xml version="1.0" encoding="UTF-8" standalone="yes"?><imgdir name="01902330.img"><imgdir name="info"><int name="reqLevel" value="70"/><string name="islot" value="Tm"/><string name="vslot" value="Tm"/><int name="tamingMob" value="10"/><canvas name="icon" width="32" height="32"><vector name="origin" x="0" y="32"/></canvas><canvas name="iconRaw" width="32" height="32"><vector name="origin" x="0" y="32"/><int name="z" value="0"/></canvas><int name="cash" value="1"/><int name="incDEX" value="20"/><string name="incINT" value="20"/><string name="incLUK" value="20"/><int name="incMAD" value="10"/><int name="incMHP" value="1000"/><int name="incMMP" value="1000"/><int name="incPAD" value="10"/><int name="incSTR" value="20"/></imgdir><imgdir name="fly"><uol name="0" value="../jump/0"/></imgdir><imgdir name="jump"><imgdir name="0"><canvas name="0" width="248" height="197"><vector name="origin" x="96" y="214"/><string name="z" value="tamingMobRear"/><vector name="lt" x="-53" y="-134"/><vector name="rb" x="76" y="-17"/><imgdir name="map"><vector name="navel" x="65" y="-98"/></imgdir></canvas><canvas name="1" width="373" height="195"><vector name="origin" x="215" y="212"/><string name="z" value="tamingMobMid"/><vector name="lt" x="-53" y="-136"/><vector name="rb" x="76" y="-19"/><imgdir name="map"><vector name="navel" x="65" y="-98"/></imgdir></canvas></imgdir></imgdir><imgdir name="ladder"><imgdir name="0"><canvas name="0" width="149" height="182"><vector name="origin" x="74" y="173"/><string name="z" value="tamingMobFront"/><vector name="lt" x="-64" y="-164"/><vector name="rb" x="58" y="1"/><imgdir name="map"><vector name="navel" x="0" y="-74"/></imgdir></canvas><int name="delay" value="120"/></imgdir><imgdir name="1"><canvas name="0" width="149" height="182"><vector name="origin" x="74" y="178"/><string name="z" value="tamingMobFront"/><vector name="lt" x="-64" y="-164"/><vector name="rb" x="58" y="1"/><imgdir name="map"><vector name="navel" x="0" y="-76"/></imgdir></canvas><int name="delay" value="120"/></imgdir></imgdir><imgdir name="prone"><imgdir name="0"><canvas name="0" width="248" height="189"><vector name="origin" x="96" y="189"/><string name="z" value="tamingMobRear"/><vector name="lt" x="-48" y="-112"/><vector name="rb" x="75" y="-2"/><imgdir name="map"><vector name="navel" x="63" y="-69"/></imgdir></canvas><canvas name="1" width="371" height="193"><vector name="origin" x="213" y="189"/><string name="z" value="tamingMobMid"/><vector name="lt" x="-48" y="-112"/><vector name="rb" x="75" y="-2"/><imgdir name="map"><vector name="navel" x="63" y="-69"/></imgdir></canvas><int name="delay" value="120"/></imgdir></imgdir><imgdir name="rope"><uol name="0" value="../ladder/0"/><uol name="1" value="../ladder/1"/></imgdir><imgdir name="stand1"><imgdir name="0"><canvas name="0" width="248" height="194"><vector name="origin" x="96" y="194"/><string name="z" value="tamingMobRear"/><vector name="lt" x="-48" y="-112"/><vector name="rb" x="75" y="-2"/><imgdir name="map"><vector name="navel" x="63" y="-73"/></imgdir></canvas><canvas name="1" width="375" height="193"><vector name="origin" x="217" y="192"/><string name="z" value="tamingMobMid"/><vector name="lt" x="-48" y="-112"/><vector name="rb" x="75" y="-2"/><imgdir name="map"><vector name="navel" x="63" y="-73"/></imgdir></canvas><int name="delay" value="120"/></imgdir><imgdir name="1"><canvas name="0" width="248" height="194"><vector name="origin" x="96" y="194"/><string name="z" value="tamingMobRear"/><vector name="lt" x="-48" y="-112"/><vector name="rb" x="75" y="-2"/><imgdir name="map"><vector name="navel" x="63" y="-73"/></imgdir></canvas><canvas name="1" width="375" height="191"><vector name="origin" x="217" y="191"/><string name="z" value="tamingMobMid"/><vector name="lt" x="-48" y="-112"/><vector name="rb" x="75" y="-2"/><imgdir name="map"><vector name="navel" x="63" y="-73"/></imgdir></canvas><int name="delay" value="120"/></imgdir><imgdir name="2"><canvas name="0" width="248" height="194"><vector name="origin" x="96" y="194"/><string name="z" value="tamingMobRear"/><vector name="lt" x="-48" y="-112"/><vector name="rb" x="75" y="-2"/><imgdir name="map"><vector name="navel" x="63" y="-73"/></imgdir></canvas><canvas name="1" width="375" height="190"><vector name="origin" x="217" y="190"/><string name="z" value="tamingMobMid"/><vector name="lt" x="-48" y="-112"/><vector name="rb" x="75" y="-2"/><imgdir name="map"><vector name="navel" x="63" y="-73"/></imgdir></canvas><int name="delay" value="120"/></imgdir><imgdir name="3"><canvas name="0" width="248" height="194"><vector name="origin" x="96" y="194"/><string name="z" value="tamingMobRear"/><vector name="lt" x="-48" y="-112"/><vector name="rb" x="75" y="-2"/><imgdir name="map"><vector name="navel" x="63" y="-73"/></imgdir></canvas><canvas name="1" width="376" height="191"><vector name="origin" x="218" y="191"/><string name="z" value="tamingMobMid"/><vector name="lt" x="-48" y="-112"/><vector name="rb" x="75" y="-2"/><imgdir name="map"><vector name="navel" x="63" y="-73"/></imgdir></canvas><int name="delay" value="120"/></imgdir><imgdir name="4"><canvas name="0" width="248" height="194"><vector name="origin" x="96" y="194"/><string name="z" value="tamingMobRear"/><vector name="lt" x="-48" y="-112"/><vector name="rb" x="75" y="-2"/><imgdir name="map"><vector name="navel" x="63" y="-73"/></imgdir></canvas><canvas name="1" width="376" height="193"><vector name="origin" x="218" y="192"/><string name="z" value="tamingMobMid"/><vector name="lt" x="-48" y="-112"/><vector name="rb" x="75" y="-2"/><imgdir name="map"><vector name="navel" x="63" y="-73"/></imgdir></canvas><int name="delay" value="120"/></imgdir><imgdir name="5"><canvas name="0" width="248" height="194"><vector name="origin" x="96" y="194"/><string name="z" value="tamingMobRear"/><vector name="lt" x="-48" y="-112"/><vector name="rb" x="75" y="-2"/><imgdir name="map"><vector name="navel" x="63" y="-73"/></imgdir></canvas><canvas name="1" width="375" height="192"><vector name="origin" x="217" y="191"/><string name="z" value="tamingMobMid"/><vector name="lt" x="-48" y="-112"/><vector name="rb" x="75" y="-2"/><imgdir name="map"><vector name="navel" x="63" y="-73"/></imgdir></canvas><int name="delay" value="120"/></imgdir><imgdir name="6"><canvas name="0" width="248" height="194"><vector name="origin" x="96" y="194"/><string name="z" value="tamingMobRear"/><vector name="lt" x="-48" y="-112"/><vector name="rb" x="75" y="-2"/><imgdir name="map"><vector name="navel" x="63" y="-73"/></imgdir></canvas><canvas name="1" width="375" height="191"><vector name="origin" x="217" y="190"/><string name="z" value="tamingMobMid"/><vector name="lt" x="-48" y="-112"/><vector name="rb" x="75" y="-2"/><imgdir name="map"><vector name="navel" x="63" y="-73"/></imgdir></canvas><int name="delay" value="120"/></imgdir><imgdir name="7"><canvas name="0" width="248" height="194"><vector name="origin" x="96" y="194"/><string name="z" value="tamingMobRear"/><vector name="lt" x="-48" y="-112"/><vector name="rb" x="75" y="-2"/><imgdir name="map"><vector name="navel" x="63" y="-73"/></imgdir></canvas><canvas name="1" width="375" height="192"><vector name="origin" x="217" y="191"/><string name="z" value="tamingMobMid"/><vector name="lt" x="-48" y="-112"/><vector name="rb" x="75" y="-2"/><imgdir name="map"><vector name="navel" x="63" y="-73"/></imgdir></canvas><int name="delay" value="120"/></imgdir><imgdir name="8"><canvas name="0" width="248" height="194"><vector name="origin" x="96" y="194"/><string name="z" value="tamingMobRear"/><vector name="lt" x="-48" y="-112"/><vector name="rb" x="75" y="-2"/><imgdir name="map"><vector name="navel" x="63" y="-73"/></imgdir></canvas><canvas name="1" width="375" height="193"><vector name="origin" x="217" y="192"/><string name="z" value="tamingMobMid"/><vector name="lt" x="-48" y="-112"/><vector name="rb" x="75" y="-2"/><imgdir name="map"><vector name="navel" x="63" y="-73"/></imgdir></canvas><int name="delay" value="120"/></imgdir><imgdir name="9"><canvas name="0" width="248" height="194"><vector name="origin" x="96" y="194"/><string name="z" value="tamingMobRear"/><vector name="lt" x="-48" y="-112"/><vector name="rb" x="75" y="-2"/><imgdir name="map"><vector name="navel" x="63" y="-73"/></imgdir></canvas><canvas name="1" width="375" height="192"><vector name="origin" x="217" y="191"/><string name="z" value="tamingMobMid"/><vector name="lt" x="-48" y="-112"/><vector name="rb" x="75" y="-2"/><imgdir name="map"><vector name="navel" x="63" y="-73"/></imgdir></canvas><int name="delay" value="120"/></imgdir><imgdir name="10"><canvas name="0" width="248" height="194"><vector name="origin" x="96" y="194"/><string name="z" value="tamingMobRear"/><vector name="lt" x="-48" y="-112"/><vector name="rb" x="75" y="-2"/><imgdir name="map"><vector name="navel" x="63" y="-73"/></imgdir></canvas><canvas name="1" width="375" height="191"><vector name="origin" x="217" y="190"/><string name="z" value="tamingMobMid"/><vector name="lt" x="-48" y="-112"/><vector name="rb" x="75" y="-2"/><imgdir name="map"><vector name="navel" x="63" y="-73"/></imgdir></canvas><int name="delay" value="120"/></imgdir><imgdir name="11"><canvas name="0" width="248" height="194"><vector name="origin" x="96" y="194"/><string name="z" value="tamingMobRear"/><vector name="lt" x="-48" y="-112"/><vector name="rb" x="75" y="-2"/><imgdir name="map"><vector name="navel" x="63" y="-73"/></imgdir></canvas><canvas name="1" width="375" height="192"><vector name="origin" x="217" y="191"/><string name="z" value="tamingMobMid"/><vector name="lt" x="-48" y="-112"/><vector name="rb" x="75" y="-2"/><imgdir name="map"><vector name="navel" x="63" y="-73"/></imgdir></canvas><int name="delay" value="120"/></imgdir></imgdir><imgdir name="stand2"><uol name="0" value="../stand1/0"/><uol name="1" value="../stand1/1"/><uol name="2" value="../stand1/2"/><uol name="3" value="../stand1/3"/><uol name="4" value="../stand1/4"/><uol name="5" value="../stand1/5"/><uol name="6" value="../stand1/6"/><uol name="7" value="../stand1/7"/><uol name="8" value="../stand1/8"/><uol name="9" value="../stand1/9"/><uol name="10" value="../stand1/10"/><uol name="11" value="../stand1/11"/></imgdir><imgdir name="tired"><imgdir name="0"><canvas name="0" width="248" height="189"><vector name="origin" x="96" y="189"/><string name="z" value="tamingMobRear"/><vector name="lt" x="-48" y="-112"/><vector name="rb" x="75" y="-2"/><imgdir name="map"><vector name="navel" x="63" y="-73"/></imgdir></canvas><canvas name="1" width="363" height="191"><vector name="origin" x="205" y="187"/><string name="z" value="tamingMobMid"/><vector name="lt" x="-48" y="-112"/><vector name="rb" x="75" y="-2"/><imgdir name="map"><vector name="navel" x="63" y="-73"/></imgdir></canvas><int name="delay" value="120"/></imgdir></imgdir><imgdir name="walk1"><imgdir name="0"><canvas name="0" width="248" height="194"><vector name="origin" x="96" y="194"/><string name="z" value="tamingMobRear"/><vector name="lt" x="-48" y="-112"/><vector name="rb" x="75" y="-2"/><imgdir name="map"><vector name="navel" x="63" y="-73"/></imgdir></canvas><canvas name="1" width="375" height="192"><vector name="origin" x="217" y="192"/><string name="z" value="tamingMobMid"/><vector name="lt" x="-48" y="-112"/><vector name="rb" x="75" y="-2"/><imgdir name="map"><vector name="navel" x="63" y="-73"/></imgdir></canvas><int name="delay" value="200"/></imgdir><imgdir name="1"><canvas name="0" width="248" height="193"><vector name="origin" x="96" y="193"/><string name="z" value="tamingMobRear"/><vector name="lt" x="-48" y="-112"/><vector name="rb" x="75" y="-2"/><imgdir name="map"><vector name="navel" x="63" y="-73"/></imgdir></canvas><canvas name="1" width="377" height="190"><vector name="origin" x="219" y="190"/><string name="z" value="tamingMobMid"/><vector name="lt" x="-48" y="-112"/><vector name="rb" x="75" y="-2"/><imgdir name="map"><vector name="navel" x="63" y="-73"/></imgdir></canvas><int name="delay" value="200"/></imgdir><imgdir name="2"><canvas name="0" width="248" height="194"><vector name="origin" x="96" y="194"/><string name="z" value="tamingMobRear"/><vector name="lt" x="-48" y="-112"/><vector name="rb" x="75" y="-2"/><imgdir name="map"><vector name="navel" x="63" y="-73"/></imgdir></canvas><canvas name="1" width="381" height="190"><vector name="origin" x="223" y="190"/><string name="z" value="tamingMobMid"/><vector name="lt" x="-48" y="-112"/><vector name="rb" x="75" y="-2"/><imgdir name="map"><vector name="navel" x="63" y="-73"/></imgdir></canvas><int name="delay" value="200"/></imgdir><imgdir name="3"><canvas name="0" width="248" height="193"><vector name="origin" x="96" y="193"/><string name="z" value="tamingMobRear"/><vector name="lt" x="-48" y="-112"/><vector name="rb" x="75" y="-2"/><imgdir name="map"><vector name="navel" x="63" y="-73"/></imgdir></canvas><canvas name="1" width="373" height="190"><vector name="origin" x="215" y="190"/><string name="z" value="tamingMobMid"/><vector name="lt" x="-48" y="-112"/><vector name="rb" x="75" y="-2"/><imgdir name="map"><vector name="navel" x="63" y="-73"/></imgdir></canvas><int name="delay" value="200"/></imgdir></imgdir><imgdir name="walk2"><uol name="0" value="../walk1/0"/><uol name="1" value="../walk1/1"/><uol name="2" value="../walk1/2"/><uol name="3" value="../walk1/3"/></imgdir></imgdir>