<?xml version="1.0" encoding="UTF-8" standalone="yes"?><imgdir name="01983045.img"><imgdir name="info"><canvas name="icon" width="31" height="32"><vector name="origin" x="0" y="31"/></canvas><canvas name="iconRaw" width="31" height="32"><vector name="origin" x="0" y="31"/></canvas></imgdir><imgdir name="sit"><imgdir name="0"><canvas name="0" width="160" height="68"><vector name="origin" x="72" y="84"/><imgdir name="map"><vector name="navel" x="3" y="-51"/></imgdir><string name="z" value="tamingMobFront"/></canvas><canvas name="1" width="38" height="45"><vector name="origin" x="3" y="93"/><string name="z" value="tamingMobRear"/></canvas></imgdir><imgdir name="1"><canvas name="0" width="159" height="68"><vector name="origin" x="72" y="83"/><imgdir name="map"><vector name="navel" x="3" y="-50"/></imgdir><string name="z" value="tamingMobFront"/></canvas><canvas name="1" width="38" height="45"><vector name="origin" x="3" y="92"/><string name="z" value="tamingMobRear"/></canvas></imgdir><imgdir name="2"><canvas name="0" width="159" height="68"><vector name="origin" x="72" y="82"/><imgdir name="map"><vector name="navel" x="3" y="-49"/></imgdir><string name="z" value="tamingMobFront"/></canvas><canvas name="1" width="38" height="45"><vector name="origin" x="3" y="91"/><string name="z" value="tamingMobRear"/></canvas></imgdir><imgdir name="3"><canvas name="0" width="162" height="69"><vector name="origin" x="72" y="82"/><imgdir name="map"><vector name="navel" x="3" y="-48"/></imgdir><string name="z" value="tamingMobFront"/></canvas><canvas name="1" width="38" height="45"><vector name="origin" x="3" y="90"/><string name="z" value="tamingMobRear"/></canvas></imgdir><imgdir name="4"><canvas name="0" width="162" height="68"><vector name="origin" x="72" y="82"/><imgdir name="map"><vector name="navel" x="3" y="-49"/></imgdir><string name="z" value="tamingMobFront"/></canvas><canvas name="1" width="38" height="45"><vector name="origin" x="3" y="91"/><string name="z" value="tamingMobRear"/></canvas></imgdir><imgdir name="5"><canvas name="0" width="160" height="68"><vector name="origin" x="72" y="83"/><imgdir name="map"><vector name="navel" x="3" y="-50"/></imgdir><string name="z" value="tamingMobFront"/></canvas><canvas name="1" width="38" height="45"><vector name="origin" x="3" y="92"/><string name="z" value="tamingMobRear"/></canvas></imgdir><imgdir name="6"><canvas name="0" width="160" height="68"><vector name="origin" x="72" y="84"/><imgdir name="map"><vector name="navel" x="3" y="-51"/></imgdir><string name="z" value="tamingMobFront"/></canvas><canvas name="1" width="38" height="45"><vector name="origin" x="3" y="93"/><string name="z" value="tamingMobRear"/></canvas></imgdir><imgdir name="7"><canvas name="0" width="162" height="68"><vector name="origin" x="72" y="83"/><imgdir name="map"><vector name="navel" x="3" y="-50"/></imgdir><string name="z" value="tamingMobFront"/></canvas><canvas name="1" width="38" height="45"><vector name="origin" x="3" y="92"/><string name="z" value="tamingMobRear"/></canvas></imgdir><imgdir name="8"><canvas name="0" width="154" height="68"><vector name="origin" x="72" y="82"/><imgdir name="map"><vector name="navel" x="3" y="-49"/></imgdir><string name="z" value="tamingMobFront"/></canvas><canvas name="1" width="38" height="45"><vector name="origin" x="3" y="91"/><string name="z" value="tamingMobRear"/></canvas></imgdir><imgdir name="9"><canvas name="0" width="157" height="69"><vector name="origin" x="72" y="82"/><imgdir name="map"><vector name="navel" x="3" y="-48"/></imgdir><string name="z" value="tamingMobFront"/></canvas><canvas name="1" width="38" height="45"><vector name="origin" x="3" y="90"/><string name="z" value="tamingMobRear"/></canvas></imgdir><imgdir name="10"><canvas name="0" width="156" height="68"><vector name="origin" x="72" y="82"/><imgdir name="map"><vector name="navel" x="3" y="-49"/></imgdir><string name="z" value="tamingMobFront"/></canvas><canvas name="1" width="38" height="45"><vector name="origin" x="3" y="91"/><string name="z" value="tamingMobRear"/></canvas></imgdir><imgdir name="11"><canvas name="0" width="162" height="68"><vector name="origin" x="72" y="83"/><imgdir name="map"><vector name="navel" x="3" y="-50"/></imgdir><string name="z" value="tamingMobFront"/></canvas><canvas name="1" width="38" height="45"><vector name="origin" x="3" y="92"/><string name="z" value="tamingMobRear"/></canvas></imgdir></imgdir></imgdir>