<?xml version="1.0" encoding="UTF-8" standalone="yes"?><imgdir name="01983197.img"><imgdir name="info"><canvas name="icon" width="34" height="30"><vector name="origin" x="1" y="29"/></canvas><canvas name="iconRaw" width="34" height="29"><vector name="origin" x="1" y="29"/></canvas></imgdir><imgdir name="sit"><imgdir name="0"><canvas name="0" width="94" height="208"><vector name="origin" x="196" y="245"/><string name="z" value="backMobEquipFront"/><imgdir name="map"><vector name="navel" x="-147" y="-116"/></imgdir></canvas></imgdir><imgdir name="1"><canvas name="0" width="110" height="204"><vector name="origin" x="223" y="245"/><string name="z" value="backMobEquipFront"/><imgdir name="map"><vector name="navel" x="-174" y="-120"/></imgdir></canvas></imgdir><imgdir name="2"><canvas name="0" width="139" height="187"><vector name="origin" x="252" y="245"/><string name="z" value="backMobEquipFront"/><imgdir name="map"><vector name="navel" x="-203" y="-137"/></imgdir></canvas></imgdir><imgdir name="3"><canvas name="0" width="174" height="160"><vector name="origin" x="287" y="245"/><string name="z" value="backMobEquipFront"/><imgdir name="map"><vector name="navel" x="-238" y="-164"/></imgdir></canvas></imgdir><imgdir name="4"><canvas name="0" width="176" height="158"><vector name="origin" x="289" y="245"/><string name="z" value="backMobEquipFront"/><imgdir name="map"><vector name="navel" x="-238" y="-165"/></imgdir></canvas></imgdir><imgdir name="5"><canvas name="0" width="177" height="157"><vector name="origin" x="290" y="245"/><string name="z" value="backMobEquipFront"/><imgdir name="map"><vector name="navel" x="-241" y="-167"/></imgdir></canvas></imgdir><imgdir name="6"><canvas name="0" width="174" height="160"><vector name="origin" x="287" y="245"/><string name="z" value="backMobEquipFront"/><imgdir name="map"><vector name="navel" x="-238" y="-164"/></imgdir></canvas></imgdir><imgdir name="7"><canvas name="0" width="139" height="187"><vector name="origin" x="252" y="245"/><string name="z" value="backMobEquipFront"/><imgdir name="map"><vector name="navel" x="-203" y="-137"/></imgdir></canvas></imgdir><imgdir name="8"><canvas name="0" width="110" height="204"><vector name="origin" x="223" y="245"/><string name="z" value="backMobEquipFront"/><imgdir name="map"><vector name="navel" x="-173" y="-120"/></imgdir></canvas></imgdir><imgdir name="9"><canvas name="0" width="94" height="208"><vector name="origin" x="196" y="245"/><string name="z" value="backMobEquipFront"/><imgdir name="map"><vector name="navel" x="-147" y="-116"/></imgdir></canvas></imgdir><imgdir name="10"><canvas name="0" width="119" height="201"><vector name="origin" x="181" y="245"/><string name="z" value="backMobEquipFront"/><imgdir name="map"><vector name="navel" x="-107" y="-123"/></imgdir></canvas></imgdir><imgdir name="11"><canvas name="0" width="126" height="195"><vector name="origin" x="181" y="245"/><string name="z" value="backMobEquipFront"/><imgdir name="map"><vector name="navel" x="-100" y="-129"/></imgdir></canvas></imgdir><imgdir name="12"><canvas name="0" width="131" height="190"><vector name="origin" x="181" y="245"/><string name="z" value="backMobEquipFront"/><imgdir name="map"><vector name="navel" x="-95" y="-134"/></imgdir></canvas></imgdir><imgdir name="13"><canvas name="0" width="133" height="188"><vector name="origin" x="181" y="245"/><string name="z" value="backMobEquipFront"/><imgdir name="map"><vector name="navel" x="-92" y="-136"/></imgdir></canvas></imgdir><imgdir name="14"><canvas name="0" width="126" height="195"><vector name="origin" x="181" y="245"/><string name="z" value="backMobEquipFront"/><imgdir name="map"><vector name="navel" x="-100" y="-129"/></imgdir></canvas></imgdir><imgdir name="15"><canvas name="0" width="119" height="201"><vector name="origin" x="181" y="245"/><string name="z" value="backMobEquipFront"/><imgdir name="map"><vector name="navel" x="-107" y="-123"/></imgdir></canvas></imgdir></imgdir></imgdir>